odoo/addons/purchase_only_by_packaging/README.rst
odoo/addons/purchase_only_by_packaging/__init__.py
odoo/addons/purchase_only_by_packaging/__manifest__.py
odoo/addons/purchase_only_by_packaging/i18n/de.po
odoo/addons/purchase_only_by_packaging/i18n/es.po
odoo/addons/purchase_only_by_packaging/i18n/fr.po
odoo/addons/purchase_only_by_packaging/i18n/it.po
odoo/addons/purchase_only_by_packaging/i18n/purchase_only_by_packaging.pot
odoo/addons/purchase_only_by_packaging/models/__init__.py
odoo/addons/purchase_only_by_packaging/models/product_packaging.py
odoo/addons/purchase_only_by_packaging/models/product_packaging_level.py
odoo/addons/purchase_only_by_packaging/models/product_product.py
odoo/addons/purchase_only_by_packaging/models/product_template.py
odoo/addons/purchase_only_by_packaging/models/purchase_order_line.py
odoo/addons/purchase_only_by_packaging/readme/CONFIGURE.rst
odoo/addons/purchase_only_by_packaging/readme/CONTRIBUTORS.rst
odoo/addons/purchase_only_by_packaging/readme/CREDITS.rst
odoo/addons/purchase_only_by_packaging/readme/DESCRIPTION.rst
odoo/addons/purchase_only_by_packaging/static/description/icon.png
odoo/addons/purchase_only_by_packaging/static/description/index.html
odoo/addons/purchase_only_by_packaging/tests/__init__.py
odoo/addons/purchase_only_by_packaging/tests/common.py
odoo/addons/purchase_only_by_packaging/tests/test_minimum_purchasable_qty.py
odoo/addons/purchase_only_by_packaging/tests/test_purchase_line_onchanges.py
odoo/addons/purchase_only_by_packaging/tests/test_purchase_only_by_packaging.py
odoo/addons/purchase_only_by_packaging/views/product_packaging.xml
odoo/addons/purchase_only_by_packaging/views/product_product.xml
odoo/addons/purchase_only_by_packaging/views/product_template.xml
odoo_addon_purchase_only_by_packaging-16.0.1.0.2.1.dist-info/METADATA
odoo_addon_purchase_only_by_packaging-16.0.1.0.2.1.dist-info/WHEEL
odoo_addon_purchase_only_by_packaging-16.0.1.0.2.1.dist-info/top_level.txt
odoo_addon_purchase_only_by_packaging-16.0.1.0.2.1.dist-info/RECORD
