Metadata-Version: 2.1
Name: odoo-addon-purchase_only_by_packaging
Version: 16.0.1.0.2.1
Summary: Manage purchase of packaging
Home-page: https://github.com/OCA/purchase-workflow
Author: Camptocamp, BCIM, Odoo Community Association (OCA)
Author-email: support@odoo-community.org
License: AGPL-3
Classifier: Programming Language :: Python
Classifier: Framework :: Odoo
Classifier: Framework :: Odoo :: 16.0
Classifier: License :: OSI Approved :: GNU Affero General Public License v3
Classifier: Development Status :: 3 - Alpha
Requires-Python: >=3.10
Requires-Dist: odoo-addon-product-packaging-level-purchasable<16.1dev,>=16.0dev
Requires-Dist: odoo<16.1dev,>=16.0a
